{
    "category": "Maui",
    "stories": [
        {
            "title": {
                "english": "Maui Slows the Sun",
                "maori": "Te Ra"
            },
            "sentences": [
                {
                    "english": "Maui noticed that the days were too short for people to complete their tasks.",
                    "maori": "I kite a Maui he poto rawa nga ra mo nga tangata ki te whakaoti i a ratou mahi.",
                    "notes": [
                        {
                            "text": "I kite a Maui he poto rawa nga ra mo nga tangata ki te whakaoti i a ratou mahi.",
                            "type": "sentence",
                            "translation": "Maui noticed that the days were too short for people to complete their tasks.",
                            "explanations": [
                                {
                                    "token": "I kite",
                                    "explanation": "I saw/noticed"
                                },
                                {
                                    "token": "a Maui",
                                    "explanation": "Maui (proper noun)"
                                },
                                {
                                    "token": "he poto rawa",
                                    "explanation": "too short"
                                },
                                {
                                    "token": "nga ra",
                                    "explanation": "the days"
                                },
                                {
                                    "token": "mo nga tangata",
                                    "explanation": "for the people"
                                },
                                {
                                    "token": "ki te whakaoti",
                                    "explanation": "to complete"
                                },
                                {
                                    "token": "i a ratou mahi",
                                    "explanation": "their tasks"
                                }
                            ]
                        }
                    ]
                },
                {
                    "english": "He decided to slow down the sun's journey across the sky.",
                    "maori": "I whakatau ia ki te whakaroa i te haerenga o te ra puta noa i te rangi.",
                    "notes": [
                        {
                            "text": "I whakatau ia ki te whakaroa i te haerenga o te ra puta noa i te rangi.",
                            "type": "sentence",
                            "translation": "He decided to slow down the sun's journey across the sky.",
                            "explanations": [
                                {
                                    "token": "I whakatau",
                                    "explanation": "decided"
                                },
                                {
                                    "token": "ia",
                                    "explanation": "he"
                                },
                                {
                                    "token": "ki te whakaroa",
                                    "explanation": "to slow down"
                                },
                                {
                                    "token": "i te haerenga",
                                    "explanation": "the journey"
                                },
                                {
                                    "token": "o te ra",
                                    "explanation": "of the sun"
                                },
                                {
                                    "token": "puta noa i te rangi",
                                    "explanation": "across the sky"
                                }
                            ]
                        }
                    ]
                },
                {
                    "english": "With the help of his brothers, Maui captured the sun with ropes and beat it with a jawbone until it promised to move more slowly.",
                    "maori": "Ma te awhina o ona tuakana, ka mau a Maui i te ra ki nga taura ka patu ki te kauae kia oati ra ano kia neke haere marie.",
                    "notes": [
                        {
                            "text": "Ma te awhina o ona tuakana, ka mau a Maui i te ra ki nga taura ka patu ki te kauae kia oati ra ano kia neke haere marie.",
                            "type": "sentence",
                            "translation": "With the help of his brothers, Maui captured the sun with ropes and beat it with a jawbone until it promised to move more slowly.",
                            "explanations": [
                                {
                                    "token": "Ma te awhina",
                                    "explanation": "With the help"
                                },
                                {
                                    "token": "o ona tuakana",
                                    "explanation": "of his brothers"
                                },
                                {
                                    "token": "ka mau",
                                    "explanation": "captured"
                                },
                                {
                                    "token": "a Maui",
                                    "explanation": "Maui (proper noun)"
                                },
                                {
                                    "token": "i te ra",
                                    "explanation": "the sun"
                                },
                                {
                                    "token": "ki nga taura",
                                    "explanation": "with ropes"
                                },
                                {
                                    "token": "ka patu",
                                    "explanation": "and beat"
                                },
                                {
                                    "token": "ki te kauae",
                                    "explanation": "with a jawbone"
                                },
                                {
                                    "token": "kia oati ra ano",
                                    "explanation": "until it promised"
                                },
                                {
                                    "token": "kia neke haere marie",
                                    "explanation": "to move more slowly"
                                }
                            ]
                        }
                    ]
                }
            ],
            "vocabulary": [
                {
                    "word": "kite",
                    "translation": "notice",
                    "explanation": "verb"
                },
                {
                    "word": "poto",
                    "translation": "short",
                    "explanation": "adjective"
                },
                {
                    "word": "ra",
                    "translation": "day",
                    "explanation": "noun"
                },
                {
                    "word": "tangata",
                    "translation": "person",
                    "explanation": "noun"
                },
                {
                    "word": "whakaoti",
                    "translation": "complete",
                    "explanation": "verb"
                },
                {
                    "word": "mahi",
                    "translation": "task",
                    "explanation": "noun"
                },
                {
                    "word": "whakatau",
                    "translation": "decide",
                    "explanation": "verb"
                },
                {
                    "word": "whakaroa",
                    "translation": "slow down",
                    "explanation": "verb"
                },
                {
                    "word": "haerenga",
                    "translation": "journey",
                    "explanation": "noun"
                },
                {
                    "word": "ra",
                    "translation": "sun",
                    "explanation": "noun"
                },
                {
                    "word": "rangi",
                    "translation": "sky",
                    "explanation": "noun"
                },
                {
                    "word": "awhina",
                    "translation": "help",
                    "explanation": "noun"
                },
                {
                    "word": "tuakana",
                    "translation": "brother",
                    "explanation": "noun"
                },
                {
                    "word": "mau",
                    "translation": "capture",
                    "explanation": "verb"
                },
                {
                    "word": "taura",
                    "translation": "rope",
                    "explanation": "noun"
                },
                {
                    "word": "patu",
                    "translation": "beat",
                    "explanation": "verb"
                },
                {
                    "word": "kauae",
                    "translation": "jawbone",
                    "explanation": "noun"
                },
                {
                    "word": "oati",
                    "translation": "promise",
                    "explanation": "verb"
                },
                {
                    "word": "neke",
                    "translation": "move",
                    "explanation": "verb"
                },
                {
                    "word": "marie",
                    "translation": "slowly",
                    "explanation": "adverb"
                }
            ]
        },
        {
            "title": {
                "english": "Maui and the Giant Fish",
                "maori": "Te Ika-a-Māui"
            },
            "sentences": [
                {
                    "english": "Maui wanted to prove his strength and skill as a fisherman.",
                    "maori": "I hiahia a Maui ki te whakaatu i tona kaha me tona pukenga hei kaihao ika.",
                    "notes": [
                        {
                            "text": "I hiahia a Maui ki te whakaatu i tona kaha me tona pukenga hei kaihao ika.",
                            "type": "sentence",
                            "translation": "Maui wanted to prove his strength and skill as a fisherman.",
                            "explanations": [
                                {
                                    "token": "I hiahia",
                                    "explanation": "wanted"
                                },
                                {
                                    "token": "a Maui",
                                    "explanation": "Maui (proper noun)"
                                },
                                {
                                    "token": "ki te whakaatu",
                                    "explanation": "to prove/show"
                                },
                                {
                                    "token": "i tona kaha",
                                    "explanation": "his strength"
                                },
                                {
                                    "token": "me tona pukenga",
                                    "explanation": "and his skill"
                                },
                                {
                                    "token": "hei kaihao ika",
                                    "explanation": "as a fisherman"
                                }
                            ]
                        }
                    ]
                },
                {
                    "english": "He crafted a magical fishhook from his grandmother's jawbone.",
                    "maori": "I hangaia e ia he matau ika makutu mai i te kauae o tona kuia.",
                    "notes": [
                        {
                            "text": "I hangaia e ia he matau ika makutu mai i te kauae o tona kuia.",
                            "type": "sentence",
                            "translation": "He crafted a magical fishhook from his grandmother's jawbone.",
                            "explanations": [
                                {
                                    "token": "I hangaia",
                                    "explanation": "crafted"
                                },
                                {
                                    "token": "e ia",
                                    "explanation": "by him"
                                },
                                {
                                    "token": "he matau ika makutu",
                                    "explanation": "a magical fishhook"
                                },
                                {
                                    "token": "mai i te kauae",
                                    "explanation": "from the jawbone"
                                },
                                {
                                    "token": "o tona kuia",
                                    "explanation": "of his grandmother"
                                }
                            ]
                        }
                    ]
                },
                {
                    "english": "Maui used the fishhook to catch a giant fish, which became the North Island of New Zealand.",
                    "maori": "I whakamahia e Maui te matau ika ki te hopu i tetahi ika nui, i riro mai hei Te Ika-a-Māui.",
                    "notes": [
                        {
                            "text": "I whakamahia e Maui te matau ika ki te hopu i tetahi ika nui, i riro mai hei Te Ika-a-Māui.",
                            "type": "sentence",
                            "translation": "Maui used the fishhook to catch a giant fish, which became the North Island of New Zealand.",
                            "explanations": [
                                {
                                    "token": "I whakamahia",
                                    "explanation": "used"
                                },
                                {
                                    "token": "e Maui",
                                    "explanation": "by Maui"
                                },
                                {
                                    "token": "te matau ika",
                                    "explanation": "the fishhook"
                                },
                                {
                                    "token": "ki te hopu",
                                    "explanation": "to catch"
                                },
                                {
                                    "token": "i tetahi ika nui",
                                    "explanation": "a giant fish"
                                },
                                {
                                    "token": "i riro mai",
                                    "explanation": "which became"
                                },
                                {
                                    "token": "hei Te Ika-a-Māui",
                                    "explanation": "the North Island of New Zealand"
                                }
                            ]
                        }
                    ]
                }
            ],
            "vocabulary": [
                {
                    "word": "hiahia",
                    "translation": "want",
                    "explanation": "verb"
                },
                {
                    "word": "whakaatu",
                    "translation": "prove",
                    "explanation": "verb"
                },
                {
                    "word": "kaha",
                    "translation": "strength",
                    "explanation": "noun"
                },
                {
                    "word": "pukenga",
                    "translation": "skill",
                    "explanation": "noun"
                },
                {
                    "word": "kaihao ika",
                    "translation": "fisherman",
                    "explanation": "noun"
                },
                {
                    "word": "hangaia",
                    "translation": "craft",
                    "explanation": "verb"
                },
                {
                    "word": "matau ika",
                    "translation": "fishhook",
                    "explanation": "noun"
                },
                {
                    "word": "makutu",
                    "translation": "magical",
                    "explanation": "adjective"
                },
                {
                    "word": "kauae",
                    "translation": "jawbone",
                    "explanation": "noun"
                },
                {
                    "word": "kuia",
                    "translation": "grandmother",
                    "explanation": "noun"
                },
                {
                    "word": "whakamahia",
                    "translation": "use",
                    "explanation": "verb"
                },
                {
                    "word": "hopu",
                    "translation": "catch",
                    "explanation": "verb"
                },
                {
                    "word": "ika",
                    "translation": "fish",
                    "explanation": "noun"
                },
                {
                    "word": "nui",
                    "translation": "giant",
                    "explanation": "adjective"
                },
                {
                    "word": "Te Ika-a-Māui",
                    "translation": "North Island of New Zealand",
                    "explanation": "noun"
                }
            ]
        },
        {
            "title": {
                "english": "Maui and the Secret of Fire",
                "maori": "Te Ahi"
            },
            "sentences": [
                {
                    "english": "Maui wanted to know how fire was made.",
                    "maori": "I hiahia a Maui ki te mohio me pehea te hanga ahi.",
                    "notes": [
                        {
                            "text": "I hiahia a Maui ki te mohio me pehea te hanga ahi.",
                            "type": "sentence",
                            "translation": "Maui wanted to know how fire was made.",
                            "explanations": [
                                {
                                    "token": "I hiahia",
                                    "explanation": "wanted"
                                },
                                {
                                    "token": "a Maui",
                                    "explanation": "Maui (proper noun)"
                                },
                                {
                                    "token": "ki te mohio",
                                    "explanation": "to know"
                                },
                                {
                                    "token": "me pehea",
                                    "explanation": "how"
                                },
                                {
                                    "token": "te hanga ahi",
                                    "explanation": "to make fire"
                                }
                            ]
                        }
                    ]
                },
                {
                    "english": "He visited Mahuika, the goddess of fire.",
                    "maori": "I haere ia ki a Mahuika, te atua o te ahi.",
                    "notes": [
                        {
                            "text": "I haere ia ki a Mahuika, te atua o te ahi.",
                            "type": "sentence",
                            "translation": "He visited Mahuika, the goddess of fire.",
                            "explanations": [
                                {
                                    "token": "I haere",
                                    "explanation": "visited"
                                },
                                {
                                    "token": "ia",
                                    "explanation": "he"
                                },
                                {
                                    "token": "ki a Mahuika",
                                    "explanation": "to Mahuika (proper noun)"
                                },
                                {
                                    "token": "te atua o te ahi",
                                    "explanation": "the goddess of fire"
                                }
                            ]
                        }
                    ]
                },
                {
                    "english": "She gave him her fingernails, which were made of flames.",
                    "maori": "I hoatu e ia ki a ia ona maikuku, he mea hanga ki te kapura.",
                    "notes": [
                        {
                            "text": "I hoatu e ia ki a ia ona maikuku, he mea hanga ki te kapura.",
                            "type": "sentence",
                            "translation": "She gave him her fingernails, which were made of flames.",
                            "explanations": [
                                {
                                    "token": "I hoatu",
                                    "explanation": "gave"
                                },
                                {
                                    "token": "e ia",
                                    "explanation": "by her"
                                },
                                {
                                    "token": "ki a ia",
                                    "explanation": "to him"
                                },
                                {
                                    "token": "ona maikuku",
                                    "explanation": "her fingernails"
                                },
                                {
                                    "token": "he mea hanga ki te kapura",
                                    "explanation": "made of flames"
                                }
                            ]
                        }
                    ]
                },
                {
                    "english": "Maui played tricks on her, causing her to lose her temper and throw fire at him.",
                    "maori": "I takaro tinihanga a Maui ki a ia, ka riri ia ka maka te ahi ki a ia.",
                    "notes": [
                        {
                            "text": "I takaro tinihanga a Maui ki a ia, ka riri ia ka maka te ahi ki a ia.",
                            "type": "sentence",
                            "translation": "Maui played tricks on her, causing her to lose her temper and throw fire at him.",
                            "explanations": [
                                {
                                    "token": "I takaro tinihanga",
                                    "explanation": "played tricks"
                                },
                                {
                                    "token": "a Maui",
                                    "explanation": "Maui (proper noun)"
                                },
                                {
                                    "token": "ki a ia",
                                    "explanation": "on her"
                                },
                                {
                                    "token": "ka riri ia",
                                    "explanation": "she lost her temper"
                                },
                                {
                                    "token": "ka maka te ahi",
                                    "explanation": "threw fire"
                                },
                                {
                                    "token": "ki a ia",
                                    "explanation": "at him"
                                }
                            ]
                        }
                    ]
                },
                {
                    "english": "He eventually learned the secret of fire and brought it back to humanity.",
                    "maori": "I te mutunga ka ako ia i te mea ngaro o te ahi ka whakahoki mai ki te tangata.",
                    "notes": [
                        {
                            "text": "I te mutunga ka ako ia i te mea ngaro o te ahi ka whakahoki mai ki te tangata.",
                            "type": "sentence",
                            "translation": "He eventually learned the secret of fire and brought it back to humanity.",
                            "explanations": [
                                {
                                    "token": "I te mutunga",
                                    "explanation": "eventually"
                                },
                                {
                                    "token": "ka ako ia",
                                    "explanation": "he learned"
                                },
                                {
                                    "token": "i te mea ngaro o te ahi",
                                    "explanation": "the secret of fire"
                                },
                                {
                                    "token": "ka whakahoki mai",
                                    "explanation": "brought back"
                                },
                                {
                                    "token": "ki te tangata",
                                    "explanation": "to humanity"
                                }
                            ]
                        }
                    ]
                }
            ],
            "vocabulary": [
                {
                    "word": "hiahia",
                    "translation": "want",
                    "explanation": "verb"
                },
                {
                    "word": "mohio",
                    "translation": "know",
                    "explanation": "verb"
                },
                {
                    "word": "hanga",
                    "translation": "make",
                    "explanation": "verb"
                },
                {
                    "word": "ahi",
                    "translation": "fire",
                    "explanation": "noun"
                },
                {
                    "word": "haere",
                    "translation": "visit",
                    "explanation": "verb"
                },
                {
                    "word": "atua",
                    "translation": "goddess",
                    "explanation": "noun"
                },
                {
                    "word": "hoatu",
                    "translation": "give",
                    "explanation": "verb"
                },
                {
                    "word": "maikuku",
                    "translation": "fingernail",
                    "explanation": "noun"
                },
                {
                    "word": "kapura",
                    "translation": "flame",
                    "explanation": "noun"
                },
                {
                    "word": "takaro",
                    "translation": "play",
                    "explanation": "verb"
                },
                {
                    "word": "tinihanga",
                    "translation": "trick",
                    "explanation": "noun"
                },
                {
                    "word": "riri",
                    "translation": "lose temper",
                    "explanation": "verb"
                },
                {
                    "word": "maka",
                    "translation": "throw",
                    "explanation": "verb"
                },
                {
                    "word": "ako",
                    "translation": "learn",
                    "explanation": "verb"
                },
                {
                    "word": "mea ngaro",
                    "translation": "secret",
                    "explanation": "noun"
                },
                {
                    "word": "whakahoki",
                    "translation": "bring back",
                    "explanation": "verb"
                },
                {
                    "word": "tangata",
                    "translation": "humanity",
                    "explanation": "noun"
                }
            ]
        },
        {
            "title": {
                "english": "Maui and the Death of Hine-nui-te-pō",
                "maori": "Te Mate o Hine-nui-te-pō"
            },
            "sentences": [
                { "english": "Maui sought immortality for humans by trying to reverse the process of birth.", "maori": "I whai a Maui i te ora tonu mo te tangata ma te ngana ki te huri i te tukanga o te whanautanga.", "notes": [ { "text": "I whai a Maui i te ora tonu mo te tangata ma te ngana ki te huri i te tukanga o te whanautanga.", "type": "sentence", "translation": "Maui sought immortality for humans by trying to reverse the process of birth.", "explanations": [ { "token": "I whai", "explanation": "sought" }, { "token": "a Maui", "explanation": "Maui (proper noun)" }, { "token": "i te ora tonu", "explanation": "immortality" }, { "token": "mo te tangata", "explanation": "for humans" }, { "token": "ma te ngana", "explanation": "by trying" }, { "token": "ki te huri", "explanation": "to reverse" }, { "token": "i te tukanga o te whanautanga", "explanation": "the process of birth" } ] } ] }, { "english": "He attempted to enter the goddess of death, Hine-nui-te-pō, through her mouth while she slept.", "maori": "I ngana ia ki te kuhu ki roto i te atua o te mate, a Hine-nui-te-pō, ma tona waha i a ia e moe ana.", "notes": [ { "text": "I ngana ia ki te kuhu ki roto i te atua o te mate, a Hine-nui-te-pō, ma tona waha i a ia e moe ana.", "type": "sentence", "translation": "He attempted to enter the goddess of death, Hine-nui-te-pō, through her mouth while she slept.", "explanations": [ { "token": "I ngana", "explanation": "attempted" }, { "token": "ia", "explanation": "he" }, { "token": "ki te kuhu ki roto", "explanation": "to enter" }, { "token": "i te atua o te mate", "explanation": "the goddess of death" }, { "token": "a Hine-nui-te-pō", "explanation": "Hine-nui-te-pō (proper noun)" }, { "token": "ma tona waha", "explanation": "through her mouth" }, { "token": "i a ia e moe ana", "explanation": "while she slept" } ] } ] }, { "english": "However, a bird laughed and woke her, causing her to crush Maui to death.", "maori": "Heoi, ka kata tetahi manu ka oho ia, ka patu ia i a Maui kia mate.", "notes": [ { "text": "Heoi, ka kata tetahi manu ka oho ia, ka patu ia i a Maui kia mate.", "type": "sentence", "translation": "However, a bird laughed and woke her, causing her to crush Maui to death.", "explanations": [ { "token": "Heoi", "explanation": "However" }, { "token": "ka kata", "explanation": "laughed" }, { "token": "tetahi manu", "explanation": "a bird" }, { "token": "ka oho ia", "explanation": "woke her" }, { "token": "ka patu ia i a Maui", "explanation": "causing her to crush Maui" }, { "token": "kia mate", "explanation": "to death" } ] } ] }, { "english": "This story explains why humans are mortal.", "maori": "Ko tenei korero e whakamaramatia ana he aha te tangata e mate ai.", "notes": [ { "text": "Ko tenei korero e whakamaramatia ana he aha te tangata e mate ai.", "type": "sentence", "translation": "This story explains why humans are mortal.", "explanations": [ { "token": "Ko tenei korero", "explanation": "This story" }, { "token": "e whakamaramatia ana", "explanation": "explains" }, { "token": "he aha te tangata", "explanation": "why humans" }, { "token": "e mate ai", "explanation": "are mortal" } ] } ] }


            ],
            "vocabulary": [
                {
                    "word": "whai",
                    "translation": "seek",
                    "explanation": "verb"
                },
                {
                    "word": "ora tonu",
                    "translation": "immortality",
                    "explanation": "noun"
                },
                {
                    "word": "tangata",
                    "translation": "human",
                    "explanation": "noun"
                },
                {
                    "word": "ngana",
                    "translation": "try",
                    "explanation": "verb"
                },
                {
                    "word": "huri",
                    "translation": "reverse",
                    "explanation": "verb"
                },
                {
                    "word": "tukanga",
                    "translation": "process",
                    "explanation": "noun"
                },
                {
                    "word": "whanautanga",
                    "translation": "birth",
                    "explanation": "noun"
                },
                {
                    "word": "kuhu",
                    "translation": "enter",
                    "explanation": "verb"
                },
                {
                    "word": "atua",
                    "translation": "goddess",
                    "explanation": "noun"
                },
                {
                    "word": "mate",
                    "translation": "death",
                    "explanation": "noun"
                },
                {
                    "word": "waha",
                    "translation": "mouth",
                    "explanation": "noun"
                },
                {
                    "word": "moe",
                    "translation": "sleep",
                    "explanation": "verb"
                },
                {
                    "word": "kata",
                    "translation": "laugh",
                    "explanation": "verb"
                },
                {
                    "word": "oho",
                    "translation": "wake",
                    "explanation": "verb"
                },
                {
                    "word": "patu",
                    "translation": "crush",
                    "explanation": "verb"
                },
                {
                    "word": "mate",
                    "translation": "death",
                    "explanation": "noun"
                },
                {
                    "word": "korero",
                    "translation": "story",
                    "explanation": "noun"
                },
                {
                    "word": "whakamaramatia",
                    "translation": "explain",
                    "explanation": "verb"
                },
                {
                    "word": "tangata",
                    "translation": "human",
                    "explanation": "noun"
                },
                {
                    "word": "mate",
                    "translation": "mortal",
                    "explanation": "noun"
                }
            ]
        },
        {
            "title": {
                "english": "Maui Lifts the Sky",
                "maori": "Te Rangi"
            },
            "sentences": [
                { "english": "In this story, the sky was once so close to the earth that people had to crawl around.", "maori": "I tenei korero, he tata rawa te rangi ki te whenua, me ngokingoki nga tangata.", "notes": [ { "text": "I tenei korero, he tata rawa te rangi ki te whenua, me ngokingoki nga tangata.", "type": "sentence", "translation": "In this story, the sky was once so close to the earth that people had to crawl around.", "explanations": [ { "token": "I tenei korero", "explanation": "In this story" }, { "token": "he tata rawa", "explanation": "was so close" }, { "token": "te rangi ki te whenua", "explanation": "the sky to the earth" }, { "token": "me ngokingoki", "explanation": "had to crawl" }, { "token": "nga tangata", "explanation": "the people" } ] } ] }, { "english": "Maui used his strength to push the sky up higher, allowing people to stand and move freely.", "maori": "I whakamahia e Maui tona kaha ki te pana i te rangi kia teitei ake, kia tu nga tangata me te neke haere noa.", "notes": [ { "text": "I whakamahia e Maui tona kaha ki te pana i te rangi kia teitei ake, kia tu nga tangata me te neke haere noa.", "type": "sentence", "translation": "Maui used his strength to push the sky up higher, allowing people to stand and move freely.", "explanations": [ { "token": "I whakamahia", "explanation": "used" }, { "token": "e Maui", "explanation": "by Maui" }, { "token": "tona kaha", "explanation": "his strength" }, { "token": "ki te pana", "explanation": "to push" }, { "token": "i te rangi", "explanation": "the sky" }, { "token": "kia teitei ake", "explanation": "up higher" }, { "token": "kia tu nga tangata", "explanation": "allowing people to stand" }, { "token": "me te neke haere noa", "explanation": "and move freely" } ] } ] }


            ],
            "vocabulary": [
                {
                    "word": "korero",
                    "translation": "story",
                    "explanation": "noun"
                },
                {
                    "word": "rangi",
                    "translation": "sky",
                    "explanation": "noun"
                },
                {
                    "word": "whenua",
                    "translation": "earth",
                    "explanation": "noun"
                },
                {
                    "word": "ngokingoki",
                    "translation": "crawl",
                    "explanation": "verb"
                },
                {
                    "word": "tangata",
                    "translation": "people",
                    "explanation": "noun"
                },
                {
                    "word": "whakamahia",
                    "translation": "use",
                    "explanation": "verb"
                },
                {
                    "word": "kaha",
                    "translation": "strength",
                    "explanation": "noun"
                },
                {
                    "word": "pana",
                    "translation": "push",
                    "explanation": "verb"
                },
                {
                    "word": "teitei",
                    "translation": "high",
                    "explanation": "adjective"
                },
                {
                    "word": "tu",
                    "translation": "stand",
                    "explanation": "verb"
                },
                {
                    "word": "neke",
                    "translation": "move",
                    "explanation": "verb"
                }
            ]
        },
        {
            "title": {
                "english": "Maui and the Birds",
                "maori": "Ngā Manu"
            },
            "sentences": [
                { "english": "Maui wanted to know why birds sang so beautifully.", "maori": "I hiahia a Maui ki te mohio he aha nga manu i waiata ai i te ataahua.", "notes": [ { "text": "I hiahia a Maui ki te mohio he aha nga manu i waiata ai i te ataahua.", "type": "sentence", "translation": "Maui wanted to know why birds sang so beautifully.", "explanations": [ { "token": "I hiahia", "explanation": "wanted" }, { "token": "a Maui", "explanation": "Maui (proper noun)" }, { "token": "ki te mohio", "explanation": "to know" }, { "token": "he aha", "explanation": "why" }, { "token": "nga manu", "explanation": "the birds" }, { "token": "i waiata ai", "explanation": "sang" }, { "token": "i te ataahua", "explanation": "so beautifully" } ] } ] }, { "english": "He transformed into a bird and joined their chorus.", "maori": "I huri ia hei manu ka uru atu ki ta ratou waiata.", "notes": [ { "text": "I huri ia hei manu ka uru atu ki ta ratou waiata.", "type": "sentence", "translation": "He transformed into a bird and joined their chorus.", "explanations": [ { "token": "I huri", "explanation": "transformed" }, { "token": "ia", "explanation": "he" }, { "token": "hei manu", "explanation": "into a bird" }, { "token": "ka uru atu", "explanation": "and joined" }, { "token": "ki ta ratou waiata", "explanation": "their chorus" } ] } ] }, { "english": "Maui learned their songs and brought the knowledge back to humans.", "maori": "I ako a Maui i a ratou waiata ka whakahoki mai i te matauranga ki te tangata.", "notes": [ { "text": "I ako a Maui i a ratou waiata ka whakahoki mai i te matauranga ki te tangata.", "type": "sentence", "translation": "Maui learned their songs and brought the knowledge back to humans.", "explanations": [ { "token": "I ako", "explanation": "learned" }, { "token": "a Maui", "explanation": "Maui (proper noun)" }, { "token": "i a ratou waiata", "explanation": "their songs" }, { "token": "ka whakahoki mai", "explanation": "brought back" }, { "token": "i te matauranga", "explanation": "the knowledge" }, { "token": "ki te tangata", "explanation": "to humans" } ] } ] }


            ],
            "vocabulary": [
                {
                    "word": "hiahia",
                    "translation": "want",
                    "explanation": "verb"
                },
                {
                    "word": "mohio",
                    "translation": "know",
                    "explanation": "verb"
                },
                {
                    "word": "manu",
                    "translation": "bird",
                    "explanation": "noun"
                },
                {
                    "word": "waiata",
                    "translation": "sing",
                    "explanation": "verb"
                },
                {
                    "word": "ataahua",
                    "translation": "beautifully",
                    "explanation": "adverb"
                },
                {
                    "word": "huri",
                    "translation": "transform",
                    "explanation": "verb"
                },
                {
                    "word": "uru",
                    "translation": "join",
                    "explanation": "verb"
                },
                {
                    "word": "ako",
                    "translation": "learn",
                    "explanation": "verb"
                },
                {
                    "word": "waiata",
                    "translation": "song",
                    "explanation": "noun"
                },
                {
                    "word": "whakahoki",
                    "translation": "bring back",
                    "explanation": "verb"
                },
                {
                    "word": "matauranga",
                    "translation": "knowledge",
                    "explanation": "noun"
                },
                {
                    "word": "tangata",
                    "translation": "human",
                    "explanation": "noun"
                }
            ]
        },
        {
            "title": {
                "english": "Maui and the Eel",
                "maori": "Te Tuna"
            },
            "sentences": [
                { "english": "Maui's wife was attacked by a giant eel while bathing.", "maori": "I whakaekea te wahine a Maui e tetahi tuna nui i a ia e kaukau ana.", "notes": [ { "text": "I whakaekea te wahine a Maui e tetahi tuna nui i a ia e kaukau ana.", "type": "sentence", "translation": "Maui's wife was attacked by a giant eel while bathing.", "explanations": [ { "token": "I whakaekea", "explanation": "was attacked" }, { "token": "te wahine a Maui", "explanation": "Maui's wife" }, { "token": "e tetahi tuna nui", "explanation": "by a giant eel" }, { "token": "i a ia e kaukau ana", "explanation": "while bathing" } ] } ] }, { "english": "Maui fought and killed the eel.", "maori": "I whawhai a Maui ka patu i te tuna.", "notes": [ { "text": "I whawhai a Maui ka patu i te tuna.", "type": "sentence", "translation": "Maui fought and killed the eel.", "explanations": [ { "token": "I whawhai", "explanation": "fought" }, { "token": "a Maui", "explanation": "Maui (proper noun)" }, { "token": "ka patu", "explanation": "killed" }, { "token": "i te tuna", "explanation": "the eel" } ] } ] }, { "english": "From its body, he created the first coconut tree.", "maori": "Mai i tona tinana, i hangaia e ia te rakau nati tuatahi.", "notes": [ { "text": "Mai i tona tinana, i hangaia e ia te rakau nati tuatahi.", "type": "sentence", "translation": "From its body, he created the first coconut tree.", "explanations": [ { "token": "Mai i tona tinana", "explanation": "From its body" }, { "token": "i hangaia e ia", "explanation": "he created" }, { "token": "te rakau nati tuatahi", "explanation": "the first coconut tree" } ] } ] }


            ],
            "vocabulary": [
                {
                    "word": "whakaekea",
                    "translation": "attack",
                    "explanation": "verb"
                },
                {
                    "word": "wahine",
                    "translation": "wife",
                    "explanation": "noun"
                },
                {
                    "word": "tuna",
                    "translation": "eel",
                    "explanation": "noun"
                },
                {
                    "word": "kaukau",
                    "translation": "bathe",
                    "explanation": "verb"
                },
                {
                    "word": "whawhai",
                    "translation": "fight",
                    "explanation": "verb"
                },
                {
                    "word": "patu",
                    "translation": "kill",
                    "explanation": "verb"
                },
                {
                    "word": "tinana",
                    "translation": "body",
                    "explanation": "noun"
                },
                {
                    "word": "hangaia",
                    "translation": "create",
                    "explanation": "verb"
                },
                {
                    "word": "rakau nati",
                    "translation": "coconut tree",
                    "explanation": "noun"
                },
                {
                    "word": "tuatahi",
                    "translation": "first",
                    "explanation": "adjective"
                }
            ]
        },
        {
            "title": {
                "english": "Maui and the Tides",
                "maori": "Ngā Tai"
            },
            "sentences": [
                { "english": "Maui noticed that the tides were unpredictable and caused problems for fishermen.", "maori": "I kite a Maui he koretake nga tai ka raru nga kaihao ika.", "notes": [ { "text": "I kite a Maui he koretake nga tai ka raru nga kaihao ika.", "type": "sentence", "translation": "Maui noticed that the tides were unpredictable and caused problems for fishermen.", "explanations": [ { "token": "I kite", "explanation": "noticed" }, { "token": "a Maui", "explanation": "Maui (proper noun)" }, { "token": "he koretake", "explanation": "unpredictable" }, { "token": "nga tai", "explanation": "the tides" }, { "token": "ka raru", "explanation": "caused problems" }, { "token": "nga kaihao ika", "explanation": "for the fishermen" } ] } ] }, { "english": "He used his magic to control the tides, making them more regular and predictable.", "maori": "I whakamahia e ia ana mahi makutu ki te whakahaere i nga tai kia auau ake, kia taea te matapae.", "notes": [ { "text": "I whakamahia e ia ana mahi makutu ki te whakahaere i nga tai kia auau ake, kia taea te matapae.", "type": "sentence", "translation": "He used his magic to control the tides, making them more regular and predictable.", "explanations": [ { "token": "I whakamahia", "explanation": "used" }, { "token": "e ia", "explanation": "by him" }, { "token": "ana mahi makutu", "explanation": "his magic" }, { "token": "ki te whakahaere", "explanation": "to control" }, { "token": "i nga tai", "explanation": "the tides" }, { "token": "kia auau ake", "explanation": "more regular" }, { "token": "kia taea te matapae", "explanation": "and predictable" } ] } ] }


            ],
            "vocabulary": [
                {
                    "word": "kite",
                    "translation": "notice",
                    "explanation": "verb"
                },
                {
                    "word": "koretake",
                    "translation": "unpredictable",
                    "explanation": "adjective"
                },
                {
                    "word": "tai",
                    "translation": "tide",
                    "explanation": "noun"
                },
                {
                    "word": "raru",
                    "translation": "problem",
                    "explanation": "noun"
                },
                {
                    "word": "kaihao ika",
                    "translation": "fisherman",
                    "explanation": "noun"
                },
                {
                    "word": "whakamahia",
                    "translation": "use",
                    "explanation": "verb"
                },
                {
                    "word": "mahi makutu",
                    "translation": "magic",
                    "explanation": "noun"
                },
                {
                    "word": "whakahaere",
                    "translation": "control",
                    "explanation": "verb"
                },
                {
                    "word": "auau",
                    "translation": "regular",
                    "explanation": "adjective"
                },
                {
                    "word": "matapae",
                    "translation": "predict",
                    "explanation": "verb"
                }
            ]
        }
    ]
}